fast_gui/__init__.py
fast_gui/_nbdev.py
fast_gui/augmentation_dashboard.py
fast_gui/code.py
fast_gui/core.py
fast_gui/dashboard_one.py
fast_gui/dashboard_two.py
fast_gui/datablock.py
fast_gui/display.py
fast_gui-0.0.4.dist-info/LICENSE
fast_gui-0.0.4.dist-info/METADATA
fast_gui-0.0.4.dist-info/WHEEL
fast_gui-0.0.4.dist-info/entry_points.txt
fast_gui-0.0.4.dist-info/top_level.txt
fast_gui-0.0.4.dist-info/RECORD
